{
"moduleCode": "MUA3155",
"moduleTitle": "Collaborative Piano Studies",
"moduleCredit": "2",
"lockedModules":[
],
"preclusion": "NIL",
"prerequisite" : "NIL",
"preclusionList": [],
"parsedPrerequisite" : "nil",
"prerequisiteList": [],
"completePrerequisite": {
            "name": "MUA3155", 
            "children": []
},

"crossModule": "-1",
"corequisite": "-1",
"faculty": "YONG SIEW TOH CONSERVATORY OF MUSIC",
"department": "YONG SIEW TOH CONSERVATORY OF MUSIC",
"history": [[0,0,0,0,0,],[0,0,0,0,0,],[0,0,0,0,0,],[0,0,0,0,0,],[0,0,0,0,0,],[2015,1,2,0,0,]]
}
