{
"moduleCode": "PA1113A",
"moduleTitle": "Basic Pharmacology",
"moduleCredit": "4",
"lockedModules":[
],
"preclusion": "NIL",
"prerequisite": "NUR5102 Advanced Pathophysiology",
"preclusionList": [],
"parsedPrerequisite": {
" and ": ["NUR5102"]
},
"prerequisiteList": ["NUR5102"],
"completePrerequisite": {
            "name": "PA1113A", 
            "children": [
                {
                    "name": "NUR5102", 
                    "children": []
                }
            ]
},
"moduleDescription": "This is a team-taught module that aims to prepare Master of Nursing students with the fundamental principles in how drugs influence human body and how human body handles these agents. These principles are key to introducing system pharmacology here which includes major topics: autonomic, corticosteroid, steroid hormone and immune-pharmacology.",
"crossModule": "-1",
"corequisite": "-1",
"faculty": "YONG LOO LIN SCHOOL OF MEDICINE",
"department": "PHARMACOLOGY",
"history": [[0,0,0,0,0,],[0,0,0,0,0,],[0,0,0,0,0,],[0,0,0,0,0,],[0,0,0,0,0,],[2015,0,2,0,0,]]
}
